package_david/__init__.py
package_david/estadisticos.py
package_david-0.0.2.dist-info/LICENSE
package_david-0.0.2.dist-info/METADATA
package_david-0.0.2.dist-info/WHEEL
package_david-0.0.2.dist-info/top_level.txt
package_david-0.0.2.dist-info/RECORD
