Metadata-Version: 2.1
Name: package-david
Version: 0.0.2
Summary: Un paquete de prueba para la monitoria de la clase de ML
Author-email: David Felipe Bautista <dfbau2002@gmail.com>
License: MIT License        
Project-URL: Homepage, https://github.com/BautistaDavid/package_david
Project-URL: Bug Tracker, https://github.com/BautistaDavid/package_david/issues
Classifier: Programming Language :: Python :: 3
Classifier: License :: OSI Approved :: MIT License
Classifier: Operating System :: OS Independent
Requires-Python: >=3.7
License-File: LICENSE
